hello_tea.py
teaxyz_addingtong-1.0.6.dist-info/METADATA
teaxyz_addingtong-1.0.6.dist-info/WHEEL
teaxyz_addingtong-1.0.6.dist-info/entry_points.txt
teaxyz_addingtong-1.0.6.dist-info/top_level.txt
teaxyz_addingtong-1.0.6.dist-info/RECORD
