Metadata-Version: 2.1
Name: teaxyz-addingtong
Version: 1.0.6
Summary: A simple package for https://app.tea.xyz/. Example tea-xyz - https://github.com/addingtonglenn9/tea_xyz
Home-page: https://github.com/addingtonglenn9/tea_xyz
Author: addingtong
Author-email: addingtonglenn9@gmail.com
Project-URL: Homepage, https://github.com/addingtonglenn9/tea_xyz
Project-URL: Source, https://github.com/addingtonglenn9/tea_xyz
Classifier: License :: OSI Approved :: MIT License
Classifier: Programming Language :: Python :: 3
Requires-Python: >=3.6
Requires-Dist: requests >=2.20.0
Requires-Dist: teaxyz-addingtong
